desc_howto_python_package/__init__.py
desc_howto_python_package/_version.py
desc_howto_python_package/hello_world.py
desc_howto_python_package/data/i_knew.txt
desc_howto_python_package/data/oh_you_will.txt
desc_howto_python_package/data/sir_john_davies.txt
desc_howto_python_package-0.0.4.dist-info/LICENSE
desc_howto_python_package-0.0.4.dist-info/METADATA
desc_howto_python_package-0.0.4.dist-info/WHEEL
desc_howto_python_package-0.0.4.dist-info/top_level.txt
desc_howto_python_package-0.0.4.dist-info/RECORD
