Metadata-Version: 2.1
Name: desc-howto-python-package
Version: 0.0.4
Summary: HOWTO on building a python package for DESC
Author-email: Eric Charles <echarles@slac.stanford.edu>
License: BSD 3-Clause License        
Classifier: Development Status :: 4 - Beta
Classifier: License :: OSI Approved :: BSD License
Classifier: Intended Audience :: Developers
Classifier: Intended Audience :: Science/Research
Classifier: Programming Language :: Python
Classifier: Programming Language :: Python :: 3
Classifier: Programming Language :: Python :: 3.10
Classifier: Natural Language :: English
Classifier: Operating System :: POSIX
Requires-Python: >=3.8
License-File: LICENSE
Requires-Dist: numpy
Provides-Extra: dev
Requires-Dist: coverage ; extra == 'dev'
Requires-Dist: pylint ; extra == 'dev'
Requires-Dist: pytest ; extra == 'dev'
Requires-Dist: pytest-cov ; extra == 'dev'
Requires-Dist: flake8 ; extra == 'dev'
